coplaniverse/__init__.py
coplaniverse-0.0.0.dist-info/LICENSE
coplaniverse-0.0.0.dist-info/METADATA
coplaniverse-0.0.0.dist-info/WHEEL
coplaniverse-0.0.0.dist-info/top_level.txt
coplaniverse-0.0.0.dist-info/RECORD
